ioc_strings/__init__.py
ioc_strings/ioc_strings.py
ioc_strings-0.1.5.dist-info/LICENSE
ioc_strings-0.1.5.dist-info/METADATA
ioc_strings-0.1.5.dist-info/WHEEL
ioc_strings-0.1.5.dist-info/entry_points.txt
ioc_strings-0.1.5.dist-info/top_level.txt
ioc_strings-0.1.5.dist-info/RECORD
