Metadata-Version: 2.1
Name: ioc-strings
Version: 0.1.5
Summary: Extract IOC strings from files, just like Linux strings command, but only IOCs.
Home-page: https://gitlab.com/CinCan/ioc_strings
Author: CinCan
Author-email: cincan@cincan.io
License: MIT
Platform: UNKNOWN
Requires-Dist: iocextract
Requires-Dist: validators
